qsinc/__init__.py
qsinc/core.py
qsinc/utils.py
qsinc-3.2.0.dist-info/licenses/LICENSE
qsinc-3.2.0.dist-info/METADATA
qsinc-3.2.0.dist-info/WHEEL
qsinc-3.2.0.dist-info/entry_points.txt
qsinc-3.2.0.dist-info/top_level.txt
qsinc-3.2.0.dist-info/RECORD
