Metadata-Version: 2.4
Name: qsinc
Version: 3.2.0
Summary: Revolutionary Quaternary Compression with Built-in Security
Home-page: https://github.com/YOUR_ankitsinc/qsinc
Author: Ankit Singh
Author-email: Ankit Singh <ankitsingh9717@gmail.com>
Maintainer: Ankit Singh
Maintainer-email: Ankit Singh <ankitsingh9717@gmail.com>
License: MIT
Project-URL: Homepage, https://github.com/ankitsinc/qsinc
Project-URL: Repository, https://github.com/ankitsinc/qsinc
Project-URL: Issues, https://github.com/ankitsinc/qsinc/issues
Project-URL: Documentation, https://github.com/ankitsinc/qsinc#readme
Keywords: compression,quaternary,security,encryption
Platform: any
Classifier: Development Status :: 4 - Beta
Classifier: Intended Audience :: Developers
Classifier: License :: OSI Approved :: MIT License
Classifier: Programming Language :: Python :: 3
Classifier: Programming Language :: Python :: 3.8
Classifier: Programming Language :: Python :: 3.9
Classifier: Programming Language :: Python :: 3.10
Classifier: Programming Language :: Python :: 3.11
Classifier: Programming Language :: Python :: 3.12
Classifier: Topic :: System :: Archiving :: Compression
Classifier: Topic :: Security :: Cryptography
Requires-Python: >=3.8
License-File: LICENSE
Provides-Extra: dev
Requires-Dist: pytest>=6.0.0; extra == "dev"
Requires-Dist: pytest-cov>=2.12.0; extra == "dev"
Requires-Dist: black>=21.0.0; extra == "dev"
Requires-Dist: flake8>=3.9.0; extra == "dev"
Requires-Dist: mypy>=0.910; extra == "dev"
Provides-Extra: fast
Requires-Dist: numpy>=1.20.0; extra == "fast"
Requires-Dist: cython>=0.29.0; extra == "fast"
Provides-Extra: all
Requires-Dist: numpy>=1.20.0; extra == "all"
Requires-Dist: cython>=0.29.0; extra == "all"
Requires-Dist: pytest>=6.0.0; extra == "all"
Requires-Dist: black>=21.0.0; extra == "all"
Dynamic: author
Dynamic: home-page
Dynamic: license-file
Dynamic: maintainer
Dynamic: platform
Dynamic: requires-python
